ploomber_dummy/__init__.py
ploomber_dummy-0.1.38.dist-info/LICENSE
ploomber_dummy-0.1.38.dist-info/METADATA
ploomber_dummy-0.1.38.dist-info/WHEEL
ploomber_dummy-0.1.38.dist-info/top_level.txt
ploomber_dummy-0.1.38.dist-info/RECORD
